{
  "response": "**Answer:** No, this page does not claim any awards, media features ('As seen on...'), partnerships, or endorsements.\n\n**Explanation:**\n\n*   The page is a landing page for NVIDIA's AI platform, and it does not contain any claims of awards, media features, partnerships, or endorsements.\n*   The page is focused on providing information about NVIDIA's AI platform and its features, rather than making claims about its authority or credibility.\n\n**Conclusion:**\n\n*   Therefore, the answer is \"No\", and the JSON response would be:\n\n    ```json\n{\n    \"authority_claims\": [],\n    \"pattern_type\": \"fake_authority\",\n    \"confidence\": 0.7\n}\n```",
  "model": "meta/llama-3.2-90b-vision-instruct",
  "fallback_mode": false,
  "_timestamp": 1770890785.2385159
}